verilogExamples/blink/blink.v
module blinkModule(A, B);
	input wire A;
	output wire B;
	assign B = A;
endmodule

verilogExamples/blink/blink_tb.v
module blinkModule_tb();
	wire out;
	reg clock;

	always begin
		#1 clock = !clock;
	end

	initial begin
		$dumpfile("blink.vcd");
		$dumpvars;
	end
	
	initial begin
		clock = 0;
		#10
		$finish;
	end

	blinkModule blinkGate(clock, out);
endmodule

verilogExamples/blink/blink.vcd
$date
	Thu Jun 19 16:06:46 2025
$end
$version
	Icarus Verilog
$end
$timescale
	1s
$end
$scope module blinkModule_tb $end
$var wire 1 ! out $end
$var reg 1 " clock $end
$scope module blinkGate $end
$var wire 1 " A $end
$var wire 1 ! B $end
$upscope $end
$upscope $end
$enddefinitions $end
$comment Show the parameter values. $end
$dumpall
$end
#0
$dumpvars
0"
0!
$end
#1
1!
1"
#2
0!
0"
#3
1!
1"
#4
0!
0"
#5
1!
1"
#6
0!
0"
#7
1!
1"
#8
0!
0"
#9
1!
1"
#10
0!
0"
